querystringer/__init__.py
querystringer/middleware.py
querystringer/test.py
querystringer-0.0.2.dist-info/LICENSE
querystringer-0.0.2.dist-info/METADATA
querystringer-0.0.2.dist-info/WHEEL
querystringer-0.0.2.dist-info/top_level.txt
querystringer-0.0.2.dist-info/RECORD
