Metadata-Version: 2.1
Name: querystringer
Version: 0.0.2
Summary: Simple middleware for django to extract string queries from urls
Home-page: https://github.com/E-RROR/QueryStringer/
Author: Sina Farhadi
Author-email: sina.farhadi.cyber@gmail.com
License: MIT
Keywords: django,strings,query,query stringer
Platform: UNKNOWN
Classifier: Framework :: Django
